lmsamplelib/__init__.py
lmsamplelib/subpackage/__init__.py
lmsamplelib/subpackage/examplemodule.cpython-371m-darwin.so
lmsamplelib/subpackage/examplemodule.cpython-372m-darwin.so
lmsamplelib/subpackage/subdir/__init__.py
lmsamplelib/subpackage/subdir/classwithresourcefile.cpython-371m-darwin.so
lmsamplelib/subpackage/subdir/classwithresourcefile.cpython-372m-darwin.so
lmsamplelib_felixvita-0.0.4.dist-info/LICENSE
lmsamplelib_felixvita-0.0.4.dist-info/METADATA
lmsamplelib_felixvita-0.0.4.dist-info/WHEEL
lmsamplelib_felixvita-0.0.4.dist-info/top_level.txt
lmsamplelib_felixvita-0.0.4.dist-info/RECORD
