Metadata-Version: 2.1
Name: lmsamplelib-felixvita
Version: 0.0.4
Summary: A package containing so files
Home-page: https://github.com/pypa/sampleproject
Author: Felix Vita
Author-email: author@example.com
License: UNKNOWN
Platform: UNKNOWN
Classifier: Programming Language :: Python :: 3
Classifier: License :: OSI Approved :: MIT License
Classifier: Operating System :: OS Independent
Requires-Python: >=3.6
